bitcaster_sdk/__init__.py
bitcaster_sdk/__main__.py
bitcaster_sdk/client.py
bitcaster_sdk/exceptions.py
bitcaster_sdk/logging.py
bitcaster_sdk/transport.py
bitcaster_sdk/version.py
bitcaster_sdk-0.2.dist-info/METADATA
bitcaster_sdk-0.2.dist-info/WHEEL
bitcaster_sdk-0.2.dist-info/entry_points.txt
bitcaster_sdk-0.2.dist-info/RECORD
