Metadata-Version: 2.4
Name: bitcaster-sdk
Version: 0.2
Summary: Bitcaster Python SDK
Author-email: mark <hanarero@gmail.com>
License: MIT
Classifier: Programming Language :: Python :: 3 :: Only
Classifier: Programming Language :: Python :: 3.8
Classifier: Programming Language :: Python :: 3.9
Classifier: Programming Language :: Python :: 3.10
Classifier: Programming Language :: Python :: 3.11
Classifier: Programming Language :: Python :: 3.12
Classifier: Programming Language :: Python :: 3.13
Requires-Python: >=3.8
Requires-Dist: click
Requires-Dist: humanfriendly
Requires-Dist: requests
